nre_dtd/__init__.py
nre_dtd/__main__.py
nre_dtd-1.1.1.dist-info/entry_points.txt
nre_dtd-1.1.1.dist-info/WHEEL
nre_dtd-1.1.1.dist-info/METADATA
nre_dtd-1.1.1.dist-info/RECORD
